nitro_datastore/__init__.py
nitro_datastore/datastore.py
nitro_datastore/py.typed
nitro_datastore/query_builder.py
nitro_datastore-1.0.3.dist-info/licenses/LICENSE
nitro_datastore-1.0.3.dist-info/METADATA
nitro_datastore-1.0.3.dist-info/WHEEL
nitro_datastore-1.0.3.dist-info/top_level.txt
nitro_datastore-1.0.3.dist-info/RECORD
