Metadata-Version: 2.4
Name: nitro-datastore
Version: 1.0.3
Summary: Schema-agnostic JSON data store with dot notation, chainable queries, bulk operations, and built-in security features
Author-email: Sean Nieuwoudt <sean@underwulf.com>
License: MIT
Project-URL: Homepage, https://github.com/nitro-sh/nitro-datastore
Project-URL: Documentation, https://github.com/nitro-sh/nitro-datastore#readme
Project-URL: Repository, https://github.com/nitro-sh/nitro-datastore
Project-URL: Issues, https://github.com/nitro-sh/nitro-datastore/issues
Keywords: json,data,datastore,configuration,storage
Classifier: Development Status :: 5 - Production/Stable
Classifier: Intended Audience :: Developers
Classifier: License :: OSI Approved :: MIT License
Classifier: Programming Language :: Python :: 3
Classifier: Programming Language :: Python :: 3.8
Classifier: Programming Language :: Python :: 3.9
Classifier: Programming Language :: Python :: 3.10
Classifier: Programming Language :: Python :: 3.11
Classifier: Programming Language :: Python :: 3.12
Classifier: Programming Language :: Python :: 3.13
Classifier: Programming Language :: Python :: 3.14
Classifier: Topic :: Software Development :: Libraries :: Python Modules
Classifier: Topic :: Utilities
Classifier: Natural Language :: English
Requires-Python: >=3.8
License-File: LICENSE
Provides-Extra: dev
Requires-Dist: pytest>=7.0; extra == "dev"
Requires-Dist: pytest-cov>=4.0; extra == "dev"
Requires-Dist: black>=24.0; extra == "dev"
Requires-Dist: flake8>=7.0; extra == "dev"
Dynamic: license-file
